simple_global_logging/__init__.py
simple_global_logging/capture.py
simple_global_logging/core.py
simple_global_logging/utils.py
simple_global_logging-0.1.2.dist-info/licenses/LICENSE
simple_global_logging-0.1.2.dist-info/METADATA
simple_global_logging-0.1.2.dist-info/WHEEL
simple_global_logging-0.1.2.dist-info/top_level.txt
simple_global_logging-0.1.2.dist-info/RECORD
