Metadata-Version: 2.4
Name: simple-global-logging
Version: 0.1.2
Summary: A simple global logging wrapper library
Author-email: hasegama <40445443+hasegama@users.noreply.github.com>
License-Expression: Apache-2.0
Project-URL: Homepage, https://github.com/hasegama/simple-global-logging
Classifier: Development Status :: 3 - Alpha
Classifier: Intended Audience :: Developers
Classifier: Operating System :: OS Independent
Classifier: Programming Language :: Python :: 3
Requires-Python: >=3.10
License-File: LICENSE
Provides-Extra: dev
Requires-Dist: pytest>=7.0; extra == "dev"
Requires-Dist: pytest-cov>=4.0; extra == "dev"
Dynamic: license-file
